rssnotify/__init__.py
rssnotify/__main__.py
rssnotify/config.py
rssnotify/rss_notify.py
rssnotify-0.1.1.dist-info/METADATA
rssnotify-0.1.1.dist-info/WHEEL
rssnotify-0.1.1.dist-info/entry_points.txt
rssnotify-0.1.1.dist-info/top_level.txt
rssnotify-0.1.1.dist-info/RECORD
