Metadata-Version: 2.1
Name: rssnotify
Version: 0.1.1
Summary: Simple RSS notify utility.
Author-email: jamazi <jamazi@tutanota.com>
Project-URL: Homepage, https://github.com/jamazi/rssnotify
Project-URL: Bug Tracker, https://github.com/jamazi/rssnotify/issues
Keywords: rss,notify
Classifier: Programming Language :: Python :: 3
Classifier: License :: OSI Approved :: MIT License
Classifier: Operating System :: OS Independent
Requires-Python: >=3.10
Requires-Dist: feedparser (==6.0.10)
Requires-Dist: pydantic[dotenv] (==1.10.7)
Provides-Extra: dev
Requires-Dist: black ; extra == 'dev'
Requires-Dist: isort ; extra == 'dev'
Requires-Dist: mypy (>=0.910) ; extra == 'dev'
Requires-Dist: pylint ; extra == 'dev'
Requires-Dist: pytest ; extra == 'dev'
